{
  "week_range": "2026-07-10 ～ 2026-07-16",
  "main_theme": "通膨預期多空拉鋸",
  "one_sentence_verdict": "本週市場面臨通膨數據降溫與能源價格上行的多空拉鋸，推升與壓低利率的力量暫時抵銷，且黃金走勢出現跨資產背離。",
  "main_question": "通膨降溫的硬數據與能源價格上行的壓力，誰將主導下一階段的利率定價？",
  "narrative_arc": "本期市場主線圍繞在通膨預期的多空拉鋸。一方面，美國 CPI 與 PPI 等硬數據顯示通膨降溫；另一方面，原油價格顯著上行帶來短線通膨隱憂。這兩股力量在債市相互抵銷，使得 10 年期公債殖利率維持平盤。同時，美元偏弱與黃金顯著下行皆缺乏典型傳導邏輯的支撐，顯示當前跨資產定價存在分歧。",
  "story_start": "本期初期，市場迎來美國 6 月 CPI 與 PPI 數據的雙雙降溫，初步緩解了對通膨僵固的擔憂。",
  "main_drivers": [
    "通膨硬數據降溫",
    "能源價格實際上行",
    "市場對通膨預期的多空拉鋸"
  ],
  "market_transmission": "通膨降溫數據壓抑了殖利率上行空間，但 WTI 與布蘭特原油的顯著走高帶來了新的通膨隱憂。兩股力量交錯下，美國 10 年期公債殖利率在本區間內呈現平盤震盪。",
  "revision_or_noise": "美元指數偏弱，但目前無法確認是利差收斂、非美貨幣反彈或資金流動所致；黃金在缺乏強美元與高利率壓抑的環境下顯著下跌，屬於跨資產背離訊號。",
  "story_end": "最終，本期市場在通膨多空訊號交錯中收尾，各類資產未能形成一致的宏觀傳導鏈，後續需等待更明確的政策或數據指引。",
  "macro_variables": {
    "inflation": "硬數據（CPI、PPI）顯示降溫，但原油價格上行增加短期能源通膨壓力，整體通膨預期呈現多空拉鋸。",
    "rate": "推升與壓低利率的力量互相抵銷，美國 10 年期公債殖利率於 4.54% 至 4.60% 區間震盪，方向尚未確認。",
    "dollar_fx": "美元指數偏弱，自 100.97 降至 100.70 附近，但具體驅動原因（利差或資金流）目前證據不足，仍待確認。",
    "asia_fx": "亞洲貨幣表現分歧，美元兌日圓微幅震盪（日圓微貶），美元兌韓元則呈現韓元走升，整體缺乏一致性方向。",
    "gold": "黃金顯著下行（自 4104 跌至 3979 美元），但同期未見美債殖利率上行或美元走強，未形成典型傳導，下跌原因待確認。",
    "energy": "WTI 與布蘭特原油雙雙顯著上行，WTI 逼近 80 美元大關，成為本期支撐通膨隱憂的主要來源。"
  },
  "evidence": [
    "美國 6 月 CPI 與 PPI 數據降溫",
    "WTI 與布蘭特原油價格顯著上行",
    "美國 10 年期公債殖利率維持平盤震盪"
  ],
  "next_week_questions": [
    "通膨上行與下行訊號誰會成為下一期主導因子？",
    "黃金的跨資產背離是否會被修復？",
    "聯準會官員是否會針對近期的通膨數據給出明確的政策轉向訊號？"
  ],
  "news_theme": "通膨降溫與高利率預期的拉鋸戰",
  "news_confirming_signals_audit_only": [
    "CPI與PPI數據全面降溫，支持市場對降息預期的重新定價",
    "美債殖利率與美元指數在通膨數據公布後同步下行，符合傳導邏輯",
    "勞動市場數據穩健，支撐Fed維持高利率的鷹派敘事"
  ],
  "news_corrections_audit_only": [
    "市場對Fed升息的押注在CPI/PPI公布後顯著降溫，修正了週初對高利率維持更久的極端擔憂"
  ],
  "top_news_audit_only": [
    "美通膨降溫 6月 CPI 年增3.5%比預期好 升息且慢 - 經濟日報",
    "美 PPI 增速放緩 6月下滑0.3% 「鷹」浪變小 - 經濟日報",
    "美股基金資金回流了 後市聚焦財報季、通膨數據 - 經濟日報",
    "股市震盪下 債券避險買氣升！八檔非投等債 ETF 股價翻紅買氣旺 | 基金天地 | 理財 - 經濟日報"
  ],
  "visual_guardrails": {
    "rate_direction": "flat",
    "rate_label": "美債殖利率平盤",
    "dxy_direction": "down",
    "dxy_label": "美元指數偏弱",
    "asia_state": "亞洲貨幣走勢分歧",
    "asia_is_mixed": true,
    "asia_detail_labels": [
      "日圓承壓（USDJPY↑）",
      "台幣承壓（USDTWD↑）",
      "韓元相對走強（USDKRW↓）"
    ],
    "gold_direction": "down",
    "gold_label": "黃金下行，但未獲利率或美元驗證",
    "gold_is_divergence": true,
    "oil_label": "油價上行",
    "high_rate_watch_only": false,
    "allowed_current_labels": [
      "本週主導因子",
      "修正因子",
      "背離訊號",
      "本週證據",
      "下週觀察",
      "美債殖利率平盤",
      "美元指數偏弱",
      "亞洲貨幣走勢分歧",
      "油價上行",
      "黃金下行，但未獲利率或美元驗證",
      "日圓承壓（USDJPY↑）",
      "台幣承壓（USDTWD↑）",
      "韓元相對走強（USDKRW↓）"
    ],
    "forbidden_current_labels": [
      "殖利率上行",
      "殖利率下行",
      "高利率更久（作為本週已確認結果）",
      "美元偏強",
      "亞幣承壓（作為亞洲貨幣整體結論）",
      "亞幣走強（作為亞洲貨幣整體結論）",
      "油價下行",
      "黃金下跌＝強美元壓力",
      "黃金下跌＝殖利率上行"
    ],
    "dxy_asia_structure": "DXY 與亞洲貨幣必須並列呈現，不得畫成單向因果鏈。",
    "news_directional_fields_excluded_from_prompt": true
  },
  "weekly_v35_diagnosis": {
    "dominant_driver": "通膨預期多空拉鋸",
    "correction_factors": [
      "通膨硬數據降溫",
      "綜合通膨預期下行",
      "通膨預期多空拉鋸",
      "市場心理與風險擔憂變化"
    ],
    "divergence_signal": "通膨降溫與能源價格上行等力量同時存在，美國10年期公債殖利率維持平盤，顯示推升與壓低利率的力量暫時互相抵銷。",
    "asset_validation": [
      "WTI 或 Brent 實際上行，短期能源通膨壓力增加。",
      "美元指數偏弱，但僅由現有資料尚無法確認是利差因素、非美貨幣反彈或其他資金流因素所致。",
      "黃金明顯下行，但同期美國10年期公債殖利率未上行、美元亦未走強，未形成典型利率與美元壓低黃金的傳導，原因待確認。"
    ],
    "next_period_watch": [
      "通膨上行與下行訊號誰會成為下一期主導因子",
      "Fed 是否延續高利率維持更久的訊號"
    ]
  },
  "rule_based_core_contradiction": "通膨降溫與能源價格上行等力量同時存在，美國10年期公債殖利率維持平盤，顯示推升與壓低利率的力量暫時互相抵銷。",
  "rule_based_primary_macro_story": "通膨預期多空拉鋸",
  "rule_based_expected_chain": [
    "通膨上行與下行訊號並存",
    "市場重新評估油價、成長、勞動與 Fed 權重",
    "美國10年期公債殖利率方向取決於主導因子",
    "美元指數反映利差與避險需求",
    "亞洲貨幣、黃金與油價可能出現分歧"
  ],
  "rule_based_observed_market": {
    "US10Y": {
      "direction": "flat",
      "text": "變化有限",
      "start_value": 4.568999767303467,
      "end_value": 4.568999767303467,
      "change": 0.0,
      "start_date": "2026-07-10",
      "end_date": "2026-07-16",
      "points_count": 5
    },
    "DXY": {
      "direction": "down",
      "text": "美元偏弱",
      "start_value": 100.97000122070312,
      "end_value": 100.70800018310547,
      "change": -0.26200103759765625,
      "start_date": "2026-07-10",
      "end_date": "2026-07-16",
      "points_count": 6
    },
    "Gold": {
      "direction": "down",
      "text": "黃金下行",
      "start_value": 4104.10009765625,
      "end_value": 3979.10009765625,
      "change": -125.0,
      "start_date": "2026-07-10",
      "end_date": "2026-07-16",
      "points_count": 6
    },
    "WTI": {
      "direction": "up",
      "text": "油價上行",
      "start_value": 71.41000366210938,
      "end_value": 79.04000091552734,
      "change": 7.629997253417969,
      "start_date": "2026-07-10",
      "end_date": "2026-07-16",
      "points_count": 6
    },
    "Brent": {
      "direction": "up",
      "text": "油價上行",
      "start_value": 76.01000213623047,
      "end_value": 85.05000305175781,
      "change": 9.040000915527344,
      "start_date": "2026-07-10",
      "end_date": "2026-07-16",
      "points_count": 6
    },
    "USDJPY": {
      "direction": "up",
      "text": "美元上行，當地貨幣承壓",
      "start_value": 161.6719970703125,
      "end_value": 162.35400390625,
      "change": 0.6820068359375,
      "start_date": "2026-07-10",
      "end_date": "2026-07-16",
      "points_count": 6
    },
    "USDTWD": {
      "direction": "up",
      "text": "美元上行，當地貨幣承壓",
      "start_value": 32.0989990234375,
      "end_value": 32.26599884033203,
      "change": 0.16699981689453125,
      "start_date": "2026-07-10",
      "end_date": "2026-07-16",
      "points_count": 6
    },
    "USDKRW": {
      "direction": "down",
      "text": "美元回落，當地貨幣相對支撐",
      "start_value": 1498.8699951171875,
      "end_value": 1477.780029296875,
      "change": -21.0899658203125,
      "start_date": "2026-07-10",
      "end_date": "2026-07-16",
      "points_count": 6
    }
  },
  "rule_based_asset_validation": [
    "WTI 或 Brent 實際上行，短期能源通膨壓力增加。",
    "美元指數偏弱，但僅由現有資料尚無法確認是利差因素、非美貨幣反彈或其他資金流因素所致。",
    "黃金明顯下行，但同期美國10年期公債殖利率未上行、美元亦未走強，未形成典型利率與美元壓低黃金的傳導，原因待確認。"
  ]
}